image_utils_fdh.py
image_utils_fdh-1.0.0.dist-info/DESCRIPTION.rst
image_utils_fdh-1.0.0.dist-info/METADATA
image_utils_fdh-1.0.0.dist-info/RECORD
image_utils_fdh-1.0.0.dist-info/WHEEL
image_utils_fdh-1.0.0.dist-info/metadata.json
image_utils_fdh-1.0.0.dist-info/top_level.txt
