Metadata-Version: 2.0
Name: image-utils-fdh
Version: 1.0.0
Summary: Mirus Image Utilities
Home-page: https://github.com/mirusresearch/image_utils_fdh
Author: Frank Henard
Author-email: frank@mirusresearch.com
License: MIT license, see LICENSE
Platform: UNKNOWN
Requires-Dist: Pillow (>=1.7.8)
